nvdsc/LICENSE
nvdsc/__init__.py
nvdsc/_version.py
nvdsc/main.py
nvdsc/setup.py
nvdsc/config/config.ini
nvdsc/config/menus.yaml
nvdsc/images/nvidia-xclam.png
nvdsc/images/nvidia.png
nvdsc/tools/__init__.py
nvdsc/tools/curated_menu_item.py
nvdsc/tools/hardware.py
nvdsc/tools/license_dialogs.py
nvdsc/tools/payload_dialogs.py
nvdsc/tools/runner.py
nvdsc/tools/versions.py
nvdsc-0.0.354.data/scripts/iudss.sh
nvdsc-0.0.354.data/scripts/jrepo
nvdsc-0.0.354.data/scripts/nvdsc
nvdsc-0.0.354.data/scripts/nvdsc-setup
nvdsc-0.0.354.data/scripts/nvdsc.desktop
nvdsc-0.0.354.data/scripts/nvdscd
nvdsc-0.0.354.dist-info/METADATA
nvdsc-0.0.354.dist-info/WHEEL
nvdsc-0.0.354.dist-info/top_level.txt
nvdsc-0.0.354.dist-info/RECORD
